hngd/.numba_config.yaml
hngd/__init__.py
hngd/animation_utils.py
hngd/default.py
hngd/hngd.py
hngd/io_utils.py
hngd/run.py
hngd-1.0.1.dist-info/LICENSE
hngd-1.0.1.dist-info/METADATA
hngd-1.0.1.dist-info/WHEEL
hngd-1.0.1.dist-info/top_level.txt
hngd-1.0.1.dist-info/RECORD
