Metadata-Version: 2.1
Name: hngd
Version: 1.0.1
Summary: Implementation of the Hydride Nucleation-Growth-Dissolution (HNGD) model. Simulates hydrogen behaviour in a 1D geometry using an explicit finite difference scheme (Euler method).
Author-email: Francisco Rotea <francisco.rotea@gmail.com>
License: BSD-3-Clause
Project-URL: Repository, https://github.com/franciscorotea/
Keywords: HNGD,Hydrogen,Hydrides,Nuclear fuel cladding,Diffusion
Classifier: Development Status :: 4 - Beta
Classifier: Programming Language :: Python :: 3
Requires-Python: >=3.10
License-File: LICENSE
Requires-Dist: numpy
Requires-Dist: matplotlib
Requires-Dist: numba
Requires-Dist: tqdm
